methylome_miner/__init__.py
methylome_miner/backend.py
methylome_miner/loading.py
methylome_miner/methylome_miner.py
methylome_miner-1.1.7.dist-info/entry_points.txt
methylome_miner-1.1.7.dist-info/licenses/LICENSE
methylome_miner-1.1.7.dist-info/WHEEL
methylome_miner-1.1.7.dist-info/METADATA
methylome_miner-1.1.7.dist-info/RECORD
