Metadata-Version: 2.4
Name: methylome_miner
Version: 1.1.7
Summary: A tool for handling DNA methylation data in extended bedMethyl format obtained from the nanopore sequencing data by Dorado and Modkit.
Author-email: Marketa Jakubickova <jakubickova@vut.cz>, Katerina Sabatova <sabatovak@vut.cz>
Maintainer-email: Katerina Sabatova <sabatovak@vut.cz>
Requires-Python: >=3.12
License-Expression: GPL-3.0-or-later
Classifier: Programming Language :: Python :: 3
Classifier: Operating System :: OS Independent
License-File: LICENSE
Requires-Dist: click>=8.1
Requires-Dist: pandas>=2.2.3
Requires-Dist: biopython>=1.84
Requires-Dist: bcbio-gff>=0.7.1
Requires-Dist: pyarrow>=18.1.0
Requires-Dist: seaborn>=0.13.2
Requires-Dist: scipy>=1.16.1
Requires-Dist: fastcluster>=1.3.0
Project-URL: Homepage, https://github.com/BioSys-BUT/MethylomeMiner
Project-URL: Issues, https://github.com/BioSys-BUT/MethylomeMiner/issues
